putl/__init__.py
putl/_modidx.py
putl/args.py
putl/arrs.py
putl/attr.py
putl/call.py
putl/dict.py
putl/iter.py
putl/jobs.py
putl/math.py
putl/tdct.py
putl/time.py
putl-0.0.15.dist-info/LICENSE
putl-0.0.15.dist-info/METADATA
putl-0.0.15.dist-info/WHEEL
putl-0.0.15.dist-info/entry_points.txt
putl-0.0.15.dist-info/top_level.txt
putl-0.0.15.dist-info/RECORD
